aioeagle/__init__.py
aioeagle/electric_meter.py
aioeagle/errors.py
aioeagle/hub.py
aioeagle/util.py
aioeagle-1.1.0.dist-info/LICENSE
aioeagle-1.1.0.dist-info/METADATA
aioeagle-1.1.0.dist-info/WHEEL
aioeagle-1.1.0.dist-info/top_level.txt
aioeagle-1.1.0.dist-info/zip-safe
aioeagle-1.1.0.dist-info/RECORD
