Metadata-Version: 2.1
Name: aioeagle
Version: 1.1.0
Summary: Python module to talk to Rainforest EAGLE-200.
Home-page: https://github.com/home-assistant-libs/aioeagle
Author: Paulus Schoutsen
Author-email: paulus@paulusschoutsen.nl
License: Apache License 2.0
Platform: any
Classifier: Intended Audience :: Developers
Classifier: Operating System :: OS Independent
Classifier: Programming Language :: Python
Classifier: Programming Language :: Python :: 3
Classifier: Topic :: Software Development :: Libraries :: Python Modules
Requires-Dist: aiohttp
Requires-Dist: xmltodict
